useragent_changer/__init__.py
useragent_changer/useragent_changer.py
useragent_changer/platform_list/android.csv
useragent_changer/platform_list/chrome.csv
useragent_changer/platform_list/edge.csv
useragent_changer/platform_list/firefox.csv
useragent_changer/platform_list/ipad.csv
useragent_changer/platform_list/iphone.csv
useragent_changer/platform_list/mac.csv
useragent_changer/platform_list/safari.csv
useragent_changer/platform_list/windows.csv
useragent_changer-0.3.2.dist-info/LICENSE.txt
useragent_changer-0.3.2.dist-info/METADATA
useragent_changer-0.3.2.dist-info/WHEEL
useragent_changer-0.3.2.dist-info/top_level.txt
useragent_changer-0.3.2.dist-info/RECORD
