Metadata-Version: 2.1
Name: useragent-changer
Version: 0.3.2
Summary: User-Agent changing library for Python.
Home-page: https://github.com/gitmori/useragent-changer
Download-URL: https://github.com/gitmori/useragent-changer
Author: Yuki Moriya
Author-email: ym19820219@gmail.com
Maintainer: Yuki Moriya
Maintainer-email: ym19820219@gmail.com
License: MIT
Keywords: useragent user_agent user-agent ua useragent_change useragent_changer useragent-changer useragent-change
Classifier: Development Status :: 5 - Production/Stable
Classifier: License :: OSI Approved :: MIT License
Classifier: Programming Language :: Python
Classifier: Programming Language :: Python :: 3
Classifier: Programming Language :: Python :: 3.6
Classifier: Programming Language :: Python :: 3.7
Classifier: Programming Language :: Python :: 3.8
Classifier: Programming Language :: Python :: 3.9
Classifier: Programming Language :: Python :: 3.10
Classifier: Programming Language :: Python :: 3.11
Requires-Python: >=3.6.5
License-File: LICENSE.txt
